README.md
setup.py
gstackutils/__init__.py
gstackutils/cert.py
gstackutils/cli.py
gstackutils/conf.py
gstackutils/exceptions.py
gstackutils/fields.py
gstackutils/termout.py
gstackutils/validators.py
gstackutils.egg-info/PKG-INFO
gstackutils.egg-info/SOURCES.txt
gstackutils.egg-info/dependency_links.txt
gstackutils.egg-info/entry_points.txt
gstackutils.egg-info/requires.txt
gstackutils.egg-info/top_level.txt